get_version/__init__.py
get_version/py.typed
get_version/testing.py
get_version-3.5.5.dist-info/LICENSE
get_version-3.5.5.dist-info/WHEEL
get_version-3.5.5.dist-info/METADATA
get_version-3.5.5.dist-info/RECORD
