Metadata-Version: 2.1
Name: get_version
Version: 3.5.5
Summary: A version helper in the spirit of versioneer.
Author-email: Philipp Angerer <phil.angerer@gmail.com>
Requires-Python: >=3.9
Classifier: Intended Audience :: Developers
Classifier: Programming Language :: Python :: 3
Classifier: Topic :: Software Development :: Libraries :: Python Modules
Classifier: License :: OSI Approved :: GNU General Public License v3 or later (GPLv3+)
Requires-Dist: dunamai>=1.19.0
Requires-Dist: pytest>=6.2.5 ; extra == "test"
Requires-Dist: pytest-black ; extra == "test"
Requires-Dist: pytest-mypy ; extra == "test"
Requires-Dist: pygments ; extra == "test"
Project-URL: Homepage, https://github.com/flying-sheep/get_version
Provides-Extra: test
